{"cities":[{"name":"Abay","url":"abay"},{"name":"Akhmetau","url":"akhmetau"},{"name":"Akkol (ekibastuz)","url":"akkol-ekibastuz"},{"name":"Akkol (taraz)","url":"akkol-taraz"},{"name":"Aksengir ","url":"aksengir"},{"name":"Akshiy (almat\u0131)","url":"akshiy-almati"},{"name":"Aksu ","url":"aksu"},{"name":"Aktau (tupqarakhan)","url":"aktau-tupqarakhan"},{"name":"Aktepe (aktyubinsk)","url":"aktepe-aktyubinsk"},{"name":"Akyrtobe ","url":"akyrtobe"},{"name":"Akzhar (taraz)","url":"akzhar-taraz"},{"name":"Alekseyevka(astana)","url":"alekseyevka-astana"},{"name":"Almati ","url":"almati"},{"name":"Almati","url":"almati-1"},{"name":"Amangeldy (taldy Kurgan)","url":"amangeldy-taldy-kurgan"},{"name":"Anar","url":"anar"},{"name":"Arasan ","url":"arasan"},{"name":"Arqalyk","url":"arqalyk"},{"name":"Arys","url":"arys"},{"name":"Ashchysay (turkistan)","url":"ashchysay-turkistan"},{"name":"Astana","url":"astana"},{"name":"Astana","url":"astana-1"},{"name":"Atabay","url":"atabay"},{"name":"Atbasar","url":"atbasar"},{"name":"Atyrau","url":"atyrau"},{"name":"Badam ","url":"badam"},{"name":"Bakyrly","url":"bakyrly"},{"name":"Baskamys","url":"baskamys"},{"name":"Bautino","url":"bautino"},{"name":"Belyye Vody","url":"belyye-vody"},{"name":"Bostandyk(taraz)","url":"bostandyk-taraz"},{"name":"Bugun(turkistan)","url":"bugun-turkistan"},{"name":"Burunday","url":"burunday"},{"name":"Chakpak","url":"chakpak"},{"name":"Chayan","url":"chayan"},{"name":"Chimkent","url":"chimkent"},{"name":"Chulakkurgan","url":"chulakkurgan"},{"name":"Cimkent","url":"cimkent"},{"name":"Dimitriyevka","url":"dimitriyevka"},{"name":"Dzhezkazgan","url":"dzhezkazgan"},{"name":"Ekibastuz","url":"ekibastuz"},{"name":"Ekibastuzskiy","url":"ekibastuzskiy"},{"name":"Ermak","url":"ermak"},{"name":"Esik ","url":"esik"},{"name":"Fogelevo ","url":"fogelevo"},{"name":"Fort Shevchenko","url":"fort-shevchenko"},{"name":"Glinkovo ","url":"glinkovo"},{"name":"Grodekovo ","url":"grodekovo"},{"name":"Ibata ","url":"ibata"},{"name":"Imeni Pamfilova","url":"imeni-pamfilova"},{"name":"Kalkaman","url":"kalkaman"},{"name":"Kamenka(astana)","url":"kamenka-astana"},{"name":"Kapal ","url":"kapal"},{"name":"Kara Bulak (cimkent)","url":"kara-bulak-cimkent"},{"name":"Karaganda","url":"karaganda"},{"name":"Karaoba(pavlodar)","url":"karaoba-pavlodar"},{"name":"Karasan","url":"karasan"},{"name":"Karatalskoye","url":"karatalskoye"},{"name":"Karatas ","url":"karatas"},{"name":"Karaturyq","url":"karaturyq"},{"name":"Karazhar(ekibastuz)","url":"karazhar-ekibastuz"},{"name":"Kentau","url":"kentau"},{"name":"Kentau","url":"kentau-1"},{"name":"Khromkau","url":"khromkau"},{"name":"Kirovskiy (taldy Kurgan)","url":"kirovskiy-taldy-kurgan"},{"name":"Klyuchi","url":"klyuchi"},{"name":"Kokchetav","url":"kokchetav"},{"name":"Koksaray(turkistan)","url":"koksaray-turkistan"},{"name":"Kopa(almat\u0131) ","url":"kopa-almati"},{"name":"Koryakovka","url":"koryakovka"},{"name":"Koschagyl","url":"koschagyl"},{"name":"Krasnoznamenka","url":"krasnoznamenka"},{"name":"Kumkent","url":"kumkent"},{"name":"Kustanay","url":"kustanay"},{"name":"Kyzyk","url":"kyzyk"},{"name":"Kyzylagash (taldy Kurgan)","url":"kyzylagash-taldy-kurgan"},{"name":"Kyzylorda","url":"kyzylorda"},{"name":"Lenger ","url":"lenger"},{"name":"Leninskiy (pavlodar)","url":"leninskiy-pavlodar"},{"name":"Lugovoe ","url":"lugovoe"},{"name":"Marinovka(astana)","url":"marinovka-astana"},{"name":"Mayakum","url":"mayakum"},{"name":"Maykain (ekibastuz)","url":"maykain-ekibastuz"},{"name":"Montaytas","url":"montaytas"},{"name":"Mulaly","url":"mulaly"},{"name":"Osakarovka","url":"osakarovka"},{"name":"Oskemen","url":"oskemen"},{"name":"Pavlodar","url":"pavlodar"},{"name":"Pavlodar","url":"pavlodar-1"},{"name":"Pavlovka","url":"pavlovka"},{"name":"Petropavlovsk","url":"petropavlovsk"},{"name":"Qapshaqhag ","url":"qapshaqhag"},{"name":"Qaratau ","url":"qaratau"},{"name":"Razumovka","url":"razumovka"},{"name":"Romanovka","url":"romanovka"},{"name":"Rozhdestvenka","url":"rozhdestvenka"},{"name":"Rudnyy","url":"rudnyy"},{"name":"Sabyndy","url":"sabyndy"},{"name":"Samsonovka (burnoye)","url":"samsonovka-burnoye"},{"name":"Sarqant","url":"sarqant"},{"name":"Sarykamysskiy","url":"sarykamysskiy"},{"name":"Semey","url":"semey"},{"name":"Shamalgan ","url":"shamalgan"},{"name":"Shcherbakty","url":"shcherbakty"},{"name":"Shengeldy(almat\u0131)","url":"shengeldy-almati"},{"name":"Shornak","url":"shornak"},{"name":"Shortandy","url":"shortandy"},{"name":"Suzak","url":"suzak"},{"name":"Taldy Kurgan","url":"taldy-kurgan"},{"name":"Taldy Kurgan ","url":"taldy-kurgan-1"},{"name":"Talghar ","url":"talghar"},{"name":"Taraz","url":"taraz"},{"name":"Tavolzhan","url":"tavolzhan"},{"name":"Teke","url":"teke"},{"name":"Terenozek","url":"terenozek"},{"name":"Timur","url":"timur"},{"name":"Tolgar","url":"tolgar"},{"name":"Tortkol","url":"tortkol"},{"name":"Turgay(astana)","url":"turgay-astana"},{"name":"Turgen ","url":"turgen"},{"name":"Turkistan","url":"turkistan"},{"name":"Turkistan","url":"turkistan-1"},{"name":"Uralsk","url":"uralsk"},{"name":"Ushtobe (taldy Kurgan)","url":"ushtobe-taldy-kurgan"},{"name":"Uspenka(pavlodar)","url":"uspenka-pavlodar"},{"name":"Yanykurgan","url":"yanykurgan"},{"name":"Zhangatas","url":"zhangatas"},{"name":"Zhansugirov","url":"zhansugirov"},{"name":"Zhidkovka","url":"zhidkovka"},{"name":"Zholymbet","url":"zholymbet"}]}