{"cities":[{"name":"Ahvaz","url":"ahvaz"},{"name":"Amol","url":"amol"},{"name":"Arak","url":"arak"},{"name":"Ardabil","url":"ardabil"},{"name":"Babol","url":"babol"},{"name":"Bojnurd","url":"bojnurd"},{"name":"Borujerd","url":"borujerd"},{"name":"Dezful","url":"dezful"},{"name":"Gorgan","url":"gorgan"},{"name":"Hamadan","url":"hamadan"},{"name":"Hurremabad","url":"hurremabad"},{"name":"Ilam","url":"ilam"},{"name":"Isfehan","url":"isfehan"},{"name":"Karaj","url":"karaj"},{"name":"Kerman","url":"kerman"},{"name":"Kermanshah","url":"kermanshah"},{"name":"Khvoy","url":"khvoy"},{"name":"Malayer","url":"malayer"},{"name":"Maragheh","url":"maragheh"},{"name":"Mashhad","url":"mashhad"},{"name":"Qaemshahr","url":"qaemshahr"},{"name":"Qazvin","url":"qazvin"},{"name":"Rajaishahr","url":"rajaishahr"},{"name":"Rasht","url":"rasht"},{"name":"Rezaiyeh","url":"rezaiyeh"},{"name":"Sanandaj","url":"sanandaj"},{"name":"Shiraz","url":"shiraz"},{"name":"Tabriz","url":"tabriz"},{"name":"Tahran","url":"tahran"},{"name":"Urmia","url":"urmia"},{"name":"Yazd","url":"yazd"},{"name":"Zahedan","url":"zahedan"},{"name":"Zanjan","url":"zanjan"}]}