{"cities":[{"name":"Bialystok","url":"bialystok"},{"name":"Bielsko-biala","url":"bielsko-biala"},{"name":"Bydgoszcz","url":"bydgoszcz"},{"name":"Bytom","url":"bytom"},{"name":"Chorzow","url":"chorzow"},{"name":"Czestochowa","url":"czestochowa"},{"name":"Dabrowa Gornicza","url":"dabrowa-gornicza"},{"name":"Elblag","url":"elblag"},{"name":"Gdansk","url":"gdansk"},{"name":"Gdynia","url":"gdynia"},{"name":"Gliwice","url":"gliwice"},{"name":"Gorzow Wielkopolski","url":"gorzow-wielkopolski"},{"name":"Grudziadz","url":"grudziadz"},{"name":"Jastrzebie Zbros","url":"jastrzebie-zbros"},{"name":"Kalisz","url":"kalisz"},{"name":"Katowice","url":"katowice"},{"name":"Kielce","url":"kielce"},{"name":"Koszalin","url":"koszalin"},{"name":"Krakow","url":"krakow"},{"name":"Legnica","url":"legnica"},{"name":"Lodz","url":"lodz"},{"name":"Lublin","url":"lublin"},{"name":"Nowy Bytom","url":"nowy-bytom"},{"name":"Olzstyn","url":"olzstyn"},{"name":"Opole","url":"opole"},{"name":"Plock","url":"plock"},{"name":"Poznan","url":"poznan"},{"name":"Radom","url":"radom"},{"name":"Rybnik","url":"rybnik"},{"name":"Rzeszow","url":"rzeszow"},{"name":"Slupsk","url":"slupsk"},{"name":"Sonsdwiec","url":"sonsdwiec"},{"name":"Szczecin","url":"szczecin"},{"name":"Tarnow","url":"tarnow"},{"name":"Torun","url":"torun"},{"name":"Tychy","url":"tychy"},{"name":"Varsova","url":"varsova"},{"name":"Walbrzych","url":"walbrzych"},{"name":"Wloclawek","url":"wloclawek"},{"name":"Wodzislaw Slaski","url":"wodzislaw-slaski"},{"name":"Wroclaw","url":"wroclaw"},{"name":"Zabrze","url":"zabrze"},{"name":"Zielona Gora","url":"zielona-gora"}]}