{"towns":[{"name":"Abana","url":"abana"},{"name":"A\u011fl\u0131","url":"agli"},{"name":"Ara\u00e7","url":"arac"},{"name":"Azdavay","url":"azdavay"},{"name":"Bozkurt (k)","url":"bozkurt-k"},{"name":"Cide","url":"cide"},{"name":"\u00c7atalzeytin","url":"catalzeytin"},{"name":"Daday","url":"daday"},{"name":"Do\u011fanyurt","url":"doganyurt"},{"name":"Han\u00f6n\u00fc","url":"hanonu"},{"name":"\u0130hsangazi","url":"ihsangazi"},{"name":"\u0130nebolu","url":"inebolu"},{"name":"Kastamonu","url":"kastamonu"},{"name":"K\u00fcre","url":"kure"},{"name":"P\u0131narba\u015f\u0131 (k)","url":"pinarbasi-k"},{"name":"\u015eenpazar","url":"senpazar"},{"name":"Ta\u015fk\u00f6pr\u00fc","url":"taskopru"},{"name":"Tosya","url":"tosya"}]}